{
  "db_name": "PostgreSQL",
  "query": "SELECT DISTINCT ON (s.site_id) s.* FROM sites s \n            LEFT JOIN deployments d ON s.site_id = d.site_id \n            WHERE s.team_id IN (SELECT team_id FROM user_teams WHERE user_id = $1) \n            OR s.team_id IN (SELECT team_id FROM teams WHERE owner_id = $1)\n            GROUP BY s.site_id, s.team_id, s.name, s.created_at\n            ORDER BY s.site_id, MAX(d.created_at) DESC NULLS LAST",
  "describe": {
    "columns": [
      {
        "ordinal": 0,
        "name": "site_id",
        "type_info": "Text"
      },
      {
        "ordinal": 1,
        "name": "team_id",
        "type_info": "Text"
      },
      {
        "ordinal": 2,
        "name": "name",
        "type_info": "Text"
      },
      {
        "ordinal": 3,
        "name": "created_at",
        "type_info": "Timestamptz"
      }
    ],
    "parameters": {
      "Left": [
        "Text"
      ]
    },
    "nullable": [
      false,
      false,
      false,
      false
    ]
  },
  "hash": "c6f7f01048b15e5eca0a5216f43cc951d75cc29da0d4e963579a2ef1ed17ad4c"
}
